[{"id":5,"name":"Rainbow Special","imgName":"almas_dinnyes_bogyos_rohadt_hus-removebg-preview.png","ingredientNeeded":["apple","watermelon","berry","rotten meat"]},{"id":6,"name":"Pink Hunter","imgName":"ceklas_repas_csirkecombos_ragu-removebg-preview.png","ingredientNeeded":["beetroot","chicken thigh","bowl"]},{"id":7,"name":"Pink Carrot Stew","imgName":"cekla_csirkecombos_ragu-removebg-preview.png","ingredientNeeded":["beetroot","chicken thigh","carrot","bowl"]},{"id":8,"name":"Chicken Sandwich","imgName":"csirkecombos_kenyér.png","ingredientNeeded":["chicken","bread"]},{"id":9,"name":"Orange Hunter","imgName":"csirkecombos_repas_ragu-removebg-preview.png","ingredientNeeded":["chicken thigh","carrot","bowl"]},{"id":10,"name":"Sweet Apple Pálinka","imgName":"cukros_alma_palinka-removebg-preview.png","ingredientNeeded":["sugar","apple","water"]},{"id":11,"name":"Potato Rainbow Stew","imgName":"krumplis_repas_ceklas_ragu-removebg-preview.png","ingredientNeeded":["potato","carrot","beetroot","bowl"]},{"id":12,"name":"Yellow Hunter","imgName":"krumplis_repas_csirkecombos_ragu-removebg-preview.png","ingredientNeeded":["cooked potatoes","chicken thigh","carrot"]},{"id":13,"name":"Skewer","imgName":"sertes_barany_csirke_nyars-removebg-preview.png","ingredientNeeded":["chicken","cooked lamb","cooked porkchop","stick"]},{"id":14,"name":"Sushi","imgName":"susi-removebg-preview.png","ingredientNeeded":["seaweed","fish"]},{"id":15,"name":"Stuffed Chicken","imgName":"toltott_csirke-removebg-preview.png","ingredientNeeded":["chicken","carrot","potato","seed"]}]